mirutil/__init__.py
mirutil/async_req.py
mirutil/classs.py
mirutil/codal.py
mirutil/compress.py
mirutil/const.py
mirutil/datalore.py
mirutil/df.py
mirutil/dirr.py
mirutil/files.py
mirutil/html.py
mirutil/jdate.py
mirutil/latex.py
mirutil/ns.py
mirutil/requests_htmll.py
mirutil/strr.py
mirutil/timing.py
mirutil/tse_ticker.py
mirutil/tsetmc.py
mirutil/utils.py
mirutil-25.2.0.dist-info/METADATA
mirutil-25.2.0.dist-info/WHEEL
mirutil-25.2.0.dist-info/licenses/LICENSE
mirutil-25.2.0.dist-info/RECORD
