Metadata-Version: 2.4
Name: mirutil
Version: 25.2.0
Summary: Tools for getting and cleaning TSE data
Project-URL: Homepage, https://github.com/imahdimir/mirutil
Project-URL: Bug Tracker, https://github.com/imahdimir/mirutil/issues
Author-email: Mahdi Mir <imahdimir@gmail.com>
License: MIT License
License-File: LICENSE
Keywords: Finance,Stocks,TSE,Tehran,cleaning,data,data_cleaning
Classifier: Intended Audience :: Developers
Classifier: License :: OSI Approved :: MIT License
Classifier: Operating System :: OS Independent
Classifier: Programming Language :: Python :: 3
Classifier: Programming Language :: Python :: Implementation :: PyPy
Classifier: Topic :: Utilities
Requires-Dist: aiohttp
Requires-Dist: fastparquet
Requires-Dist: giteasy
Requires-Dist: githubdata
Requires-Dist: gitignore-parser
Requires-Dist: html5lib
Requires-Dist: ipython
Requires-Dist: lxml
Requires-Dist: multiprocess
Requires-Dist: nest-asyncio
Requires-Dist: openpyxl
Requires-Dist: pandas
Requires-Dist: persiantools
Requires-Dist: pip
Requires-Dist: pyarrow
Requires-Dist: requests
Requires-Dist: requests-html
Requires-Dist: tabulate
Requires-Dist: zstandard
